exasol/ai/text/version.cpython-310-x86_64-linux-gnu.so
exasol/ai/text/deployment/language_container.cpython-310-x86_64-linux-gnu.so
exasol/ai/text/deployment/license_deployment.cpython-310-x86_64-linux-gnu.so
exasol/ai/text/deployment/script_deployer.cpython-310-x86_64-linux-gnu.so
exasol/ai/text/deployment/txaie_language_container_deployer.cpython-310-x86_64-linux-gnu.so
exasol/ai/text/extraction/__init__.cpython-310-x86_64-linux-gnu.so
exasol/ai/text/extraction/abstract_extraction.cpython-310-x86_64-linux-gnu.so
exasol/ai/text/extraction/extraction.cpython-310-x86_64-linux-gnu.so
exasol/ai/text/extraction/extraction_runner.cpython-310-x86_64-linux-gnu.so
exasol/ai/text/extractors/__init__.cpython-310-x86_64-linux-gnu.so
exasol/ai/text/extractors/ai_model.cpython-310-x86_64-linux-gnu.so
exasol/ai/text/extractors/ai_model_repository.cpython-310-x86_64-linux-gnu.so
exasol/ai/text/extractors/base_extractor.cpython-310-x86_64-linux-gnu.so
exasol/ai/text/extractors/base_model.cpython-310-x86_64-linux-gnu.so
exasol/ai/text/extractors/branch_extractor_helper.cpython-310-x86_64-linux-gnu.so
exasol/ai/text/extractors/bucketfs_model_repository.cpython-310-x86_64-linux-gnu.so
exasol/ai/text/extractors/co_occurrence_extractor.cpython-310-x86_64-linux-gnu.so
exasol/ai/text/extractors/default_models.cpython-310-x86_64-linux-gnu.so
exasol/ai/text/extractors/extractor.cpython-310-x86_64-linux-gnu.so
exasol/ai/text/extractors/filter_extractor.cpython-310-x86_64-linux-gnu.so
exasol/ai/text/extractors/hf_model.cpython-310-x86_64-linux-gnu.so
exasol/ai/text/extractors/keyword_extractor.cpython-310-x86_64-linux-gnu.so
exasol/ai/text/extractors/keyword_search_extractor.cpython-310-x86_64-linux-gnu.so
exasol/ai/text/extractors/named_entity_extractor.cpython-310-x86_64-linux-gnu.so
exasol/ai/text/extractors/source_table_extractor.cpython-310-x86_64-linux-gnu.so
exasol/ai/text/extractors/splitter_extractor.cpython-310-x86_64-linux-gnu.so
exasol_text_ai_extension-0.2.1.dist-info/METADATA
exasol_text_ai_extension-0.2.1.dist-info/WHEEL
exasol_text_ai_extension-0.2.1.dist-info/RECORD
exasol_text_ai_extension-0.2.1.dist-info/licenses/LICENSE
