Metadata-Version: 2.4
Name: exasol-text-ai-extension
Version: 0.2.1
Summary: Software components for text-based AI applications, such as information extraction.
Author-email: Christoph Kuhnke <christoph.kuhnke@exasol.com>, Christoph Kuhnke <christoph.kuhnke@exasol.com>
License-Expression: LicenseRef-Proprietary
License-File: LICENSE
Keywords: exasol,text_ai_extension
Requires-Python: <3.13,>=3.10
Requires-Dist: exasol-advanced-analytics-framework<1,>=0.4.1
Requires-Dist: exasol-extension-license-protocol<1,>=0.1.0
Requires-Dist: exasol-keyphrase-vectorizers<2.0.0,>=1.0.0
Requires-Dist: exasol-python-extension-common<1,>=0.9.0
Requires-Dist: exasol-transformers-extension==3.*
Requires-Dist: keybert==0.8.*
Requires-Dist: numpy==1.*
Requires-Dist: pydantic==2.*
Requires-Dist: spacy<=3.8.6
Requires-Dist: transformers>=4.48.0
